twilio_auth/__init__.py
twilio_auth/send_whatsapp.py
twilio_auth_sdk-0.1.0.dist-info/METADATA
twilio_auth_sdk-0.1.0.dist-info/WHEEL
twilio_auth_sdk-0.1.0.dist-info/top_level.txt
twilio_auth_sdk-0.1.0.dist-info/RECORD
