Metadata-Version: 2.4
Name: twilio-auth-sdk
Version: 0.1.0
Summary: Send WhatsApp authentication messages using Twilio
Home-page: https://github.com/teeteelaryo/twilio-auth-sdk
Author: Titilayo Odufowoke
Classifier: Programming Language :: Python :: 3
Classifier: License :: OSI Approved :: MIT License
Requires-Python: >=3.6
Requires-Dist: twilio
Requires-Dist: python-dotenv
Dynamic: author
Dynamic: classifier
Dynamic: description
Dynamic: description-content-type
Dynamic: home-page
Dynamic: requires-dist
Dynamic: requires-python
Dynamic: summary
